libvegas/__init__.py
libvegas/binding.py
libvegas/libs/darwin_amd64_libvegas.so
libvegas/libs/darwin_arm64_libvegas.so
libvegas/libs/linux_amd64_libvegas.so
libvegas/libs/linux_arm64_libvegas.so
libvegas-0.3.10.dist-info/LICENCE
libvegas-0.3.10.dist-info/METADATA
libvegas-0.3.10.dist-info/WHEEL
libvegas-0.3.10.dist-info/RECORD
